app_store_server_library_python_async-0.1.1.dist-info/METADATA
app_store_server_library_python_async-0.1.1.dist-info/WHEEL
app_store_server_library_python_async-0.1.1.dist-info/licenses/LICENSE.txt
app_store_server_library_python_async-0.1.1.dist-info/licenses/NOTICE.txt
appstoreserverlibraryasync/__init__.py
appstoreserverlibraryasync/api_client.py
appstoreserverlibraryasync/models/AccountTenure.py
appstoreserverlibraryasync/models/AppTransaction.py
appstoreserverlibraryasync/models/AutoRenewStatus.py
appstoreserverlibraryasync/models/CheckTestNotificationResponse.py
appstoreserverlibraryasync/models/ConsumptionRequest.py
appstoreserverlibraryasync/models/ConsumptionRequestReason.py
appstoreserverlibraryasync/models/ConsumptionStatus.py
appstoreserverlibraryasync/models/Data.py
appstoreserverlibraryasync/models/DeliveryStatus.py
appstoreserverlibraryasync/models/Environment.py
appstoreserverlibraryasync/models/ExpirationIntent.py
appstoreserverlibraryasync/models/ExtendReasonCode.py
appstoreserverlibraryasync/models/ExtendRenewalDateRequest.py
appstoreserverlibraryasync/models/ExtendRenewalDateResponse.py
appstoreserverlibraryasync/models/ExternalPurchaseToken.py
appstoreserverlibraryasync/models/FirstSendAttemptResult.py
appstoreserverlibraryasync/models/HistoryResponse.py
appstoreserverlibraryasync/models/InAppOwnershipType.py
appstoreserverlibraryasync/models/JWSRenewalInfoDecodedPayload.py
appstoreserverlibraryasync/models/JWSTransactionDecodedPayload.py
appstoreserverlibraryasync/models/LastTransactionsItem.py
appstoreserverlibraryasync/models/LibraryUtility.py
appstoreserverlibraryasync/models/LifetimeDollarsPurchased.py
appstoreserverlibraryasync/models/LifetimeDollarsRefunded.py
appstoreserverlibraryasync/models/MassExtendRenewalDateRequest.py
appstoreserverlibraryasync/models/MassExtendRenewalDateResponse.py
appstoreserverlibraryasync/models/MassExtendRenewalDateStatusResponse.py
appstoreserverlibraryasync/models/NotificationHistoryRequest.py
appstoreserverlibraryasync/models/NotificationHistoryResponse.py
appstoreserverlibraryasync/models/NotificationHistoryResponseItem.py
appstoreserverlibraryasync/models/NotificationTypeV2.py
appstoreserverlibraryasync/models/OfferDiscountType.py
app_store_server_library_python_async-0.1.1.dist-info/RECORD
