Metadata-Version: 2.1
Name: app-store-server-library-python-async
Version: 0.1.1
Summary: app-store-server-library-python-async
Author-Email: =?utf-8?q?Bahad=C4=B1r_Araz?= <bahadiraraz@protonmail.com>
License: MIT
Requires-Python: >=3.12
Requires-Dist: attrs>=21.3.0
Requires-Dist: PyJWT<3,>=2.6.0
Requires-Dist: cryptography<43,>=40.0.0
Requires-Dist: pyOpenSSL<25,>=23.1.1
Requires-Dist: asn1==2.7.0
Requires-Dist: cattrs==23.1.2
Requires-Dist: httpx>=0.27.0
